docusign_esign/__init__.py
docusign_esign/apis/__init__.py
docusign_esign/apis/accounts_api.py
docusign_esign/apis/authentication_api.py
docusign_esign/apis/billing_api.py
docusign_esign/apis/bulk_envelopes_api.py
docusign_esign/apis/bulk_process_data_api.py
docusign_esign/apis/bulk_process_data_send_api.py
docusign_esign/apis/cloud_storage_api.py
docusign_esign/apis/connect_api.py
docusign_esign/apis/custom_tabs_api.py
docusign_esign/apis/data_feed_api.py
docusign_esign/apis/diagnostics_api.py
docusign_esign/apis/email_archive_api.py
docusign_esign/apis/envelopes_api.py
docusign_esign/apis/folders_api.py
docusign_esign/apis/groups_api.py
docusign_esign/apis/notary_api.py
docusign_esign/apis/organizations_api.py
docusign_esign/apis/power_forms_api.py
docusign_esign/apis/signature_api.py
docusign_esign/apis/signing_groups_api.py
docusign_esign/apis/templates_api.py
docusign_esign/apis/trust_service_providers_api.py
docusign_esign/apis/users_api.py
docusign_esign/apis/workspaces_api.py
docusign_esign/client/__init__.py
docusign_esign/client/api_client.py
docusign_esign/client/api_exception.py
docusign_esign/client/api_response.py
docusign_esign/client/configuration.py
docusign_esign/client/auth/__init__.py
docusign_esign/client/auth/oauth.py
docusign_esign/models/__init__.py
docusign_esign/models/access_code_format.py
docusign_esign/models/account_address.py
docusign_esign/models/account_billing_plan.py
docusign_esign/models/account_billing_plan_response.py
docusign_esign/models/account_identity_input_option.py
docusign_esign/models/account_identity_verification_response.py
docusign_esign/models/account_identity_verification_step.py
docusign_esign/models/account_identity_verification_workflow.py
docusign_esign/models/account_information.py
docusign_esign/models/account_minimum_password_length.py
docusign_esign/models/account_notification.py
docusign_esign/models/account_password_expire_password_days.py
docusign_esign_rog-3.16.0.dist-info/LICENSE
docusign_esign_rog-3.16.0.dist-info/METADATA
docusign_esign_rog-3.16.0.dist-info/WHEEL
docusign_esign_rog-3.16.0.dist-info/top_level.txt
docusign_esign_rog-3.16.0.dist-info/RECORD
