Metadata-Version: 2.1
Name: docusign-esign-rog
Version: 3.16.0
Summary: DocuSign REST API
Home-page: 
Author-email: danny.murray@realtyonegroup.com
Keywords: Swagger,DocuSign REST API
License-File: LICENSE
Requires-Dist: urllib3 (>=1.15)
Requires-Dist: six (>=1.8.0)
Requires-Dist: certifi (>=14.05.14)
Requires-Dist: python-dateutil (>=2.5.3)
Requires-Dist: setuptools (>=21.0.0)
Requires-Dist: PyJWT (>=1.7.1)
Requires-Dist: cryptography (>=2.5)
Requires-Dist: nose (>=1.3.7)
